Workbook

Sheet Plan Financiero
B1: L A W A N G
B2: Lamborghini Wild Coast Sumba · Development Financial Plan · Phase I
B3: OWN · THE · ETERNITY
B6: PROJECT SNAPSHOT — PHASE I
B7: Nº villas | D7: =Supuestos!C5
B8: Precio de venta por villa | D8: =Supuestos!C6
B9: Superficie por villa | D9: =Supuestos!C7&" m²"
B10: Ventas totales (GDV) | D10: =Supuestos!C5*Supuestos!C6
B11: Inicio comercialización | D11: Mes 2 – 4
B12: Entrega estimada | D12: Mes 12 – 14
B14: ESTADO DE RESULTADOS — PHASE I
B15: CONCEPTO | C15: CÁLCULO | D15: IMPORTE | E15: % S/ VENTAS
B16: Ventas de villas | C16: 10 × 1.000.000 € | D16: =Supuestos!C5*Supuestos!C6 | E16: =D16/$D$16
B17: TOTAL INGRESOS | D17: =D16 | E17: =D17/$D$16
B18: Construcción | C18: 10 × 300.000 € | D18: =-Supuestos!C5*Supuestos!C8 | E18: =D18/$D$16
B19: Suelo (adquisición) | D19: =-Supuestos!C11 | E19: =D19/$D$16
B20: Urbanización & infraestructura | D20: =-Supuestos!C12 | E20: =D20/$D$16
B21: Licencias & permisos | D21: =-Supuestos!C13 | E21: =D21/$D$16
B22: Nick Maltese Studio (diseño & arq.) | C22: 8% s/ construcción | D22: =-(Supuestos!C5*Supuestos!C8)*Supuestos!C14 | E22: =D22/$D$16
B23: Arquitecto local & ingeniería | D23: =-Supuestos!C15 | E23: =D23/$D$16
B24: Otros profesionales técnicos | D24: =-Supuestos!C16 | E24: =D24/$D$16
B25: Marketing & branding | D25: =-Supuestos!C17 | E25: =D25/$D$16
B26: Comisiones comerciales | C26: % de ventas | D26: =-$D$16*Supuestos!C18 | E26: =D26/$D$16
B27: Gastos legales & notaría | D27: =-Supuestos!C19 | E27: =D27/$D$16
B28: Gastos administrativos | D28: =-Supuestos!C20 | E28: =D28/$D$16
B29: Seguros & contingencias | C29: % de ventas | D29: =-$D$16*Supuestos!C21 | E29: =D29/$D$16
B30: MARGEN OPERATIVO ANTES DE REPARTOS | D30: =D16+SUM(D18:D29) | E30: =D30/$D$16
B32: REPARTO DEL BENEFICIO
B33: Tonino Lamborghini | C33: 3% del beneficio | D33: =-D30*Supuestos!C22
B34: Introducción de marca | C34: 1% del beneficio | D34: =-D30*Supuestos!C23
B35: BENEFICIO NETO PARA LAWANG (Fran & Pablo) | D35: =D30+D33+D34
B37: MÉTRICAS CLAVE — PHASE I
B38: VENTAS (GDV)
B39: =D16
B41: BENEFICIO NETO LAWANG
B42: =D35
B44: MARGEN NETO SOBRE VENTAS
B45: =D35/D16
B47: ROI SOBRE COSTE TOTAL
B48: =D35/-SUM(D18:D29)
B50: ROI SOBRE INVERSIÓN TOTAL
B51: =D35/(D16*(Supuestos!C25+Supuestos!C26))
B54: CASH FLOW ESTIMADO — PHASE I
B55: HITO | C55: MES | D55: FLUJO | E55: ACUMULADO
B56: Preventas & Reservas (30%) | C56: 2 – 4 | D56: =H56-I56 | E56: =D56 | H56: 3000000 | I56: 0
B57: Inicio construcción | C57: 6 | D57: =H57-I57 | E57: =E56+D57 | H57: 0 | I57: 1500000
B58: Avance obra 30% | C58: 8 | D58: =H58-I58 | E58: =E57+D58 | H58: 0 | I58: 1200000
B59: Avance obra 60% | C59: 10 | D59: =H59-I59 | E59: =E58+D59 | H59: 0 | I59: 1000000
B60: Avance obra 90% | C60: 12 | D60: =H60-I60 | E60: =E59+D60 | H60: 0 | I60: 800000
B61: Entrega & escrituración (70%) | C61: 12 – 14 | D61: =H61-I61 | E61: =E60+D61 | H61: 7000000 | I61: 418400
B63: VALOR DEL SUELO
B64: Coste de adquisición | C64: =Supuestos!C11/Supuestos!C9&" €/m²" | D64: =Supuestos!C11
B65: Valor potencial del suelo | C65: 20000 m² × 200 €/m² | D65: =Supuestos!C9*Supuestos!C10
B66: Plusvalía estimada | D66: =D65-D64
B68: AxisWorks · Documento de inversión confidencial — Lawang Estate

Sheet Supuestos
B2: SUPUESTOS — EDITABLES
B3: Cambia un valor y todo el Plan Financiero se recalcula.
B5: Nº villas (fase) | C5: 10 | D5: villas
B6: Precio de venta por villa | C6: 1000000 | D6: €
B7: Superficie por villa | C7: 500 | D7: m²
B8: Coste de construcción por villa | C8: 300000 | D8: €
B9: Superficie total del proyecto | C9: 20000 | D9: m²
B10: Precio / valor objetivo del suelo | C10: 200 | D10: €/m²
B11: Coste de adquisición del suelo | C11: 2000000 | D11: €
B12: Urbanización & infraestructura | C12: 500000 | D12: €
B13: Licencias & permisos | C13: 100000 | D13: €
B14: Nick Maltese Studio (% s/ construcción) | C14: 0.08 | D14: %
B15: Arquitecto local & ingeniería | C15: 120000 | D15: €
B16: Otros profesionales técnicos | C16: 80000 | D16: €
... B26: Deuda / crédito puente (% s/ ventas) | C26: 0.25 | D26: %
