Workbook

Sheet Phase I Dashboard
A1: LAMBORGHINI WILD COAST SUMBA RETREAT | DEVELOPMENT FINANCIAL PLAN – PHASE I | 10 SIGNATURE VILLAS
A4: HERO VISUAL AREA Exclusive branded luxury villas Iconic design · Italian heritage · Sumba soul · Lamborghini luxury | I4: ESTADO DE RESULTADOS – PHASE I (10 VILLAS) | Q4: WATERFALL – CREACIÓN DE VALOR
I5: CONCEPTO | J5: CÁLCULO | K5: IMPORTE (€) | L5: % SOBRE VENTAS
I6: 1. INGRESOS | Q6: VENTAS BRUTAS | R6: =Calculations!B2 | S6: REPARTO DEL BENEFICIO SOBRE MARGEN OPERATIVO
I7: Ventas de 10 villas | J7: 10 villas x 1.000.000 € | K7: =Calculations!B2 | L7: =K7/Calculations!B2 | Q7: Costes Directos | R7: =-Calculations!B7 | S7: Tonino Lamborghini | T7: 3% del beneficio | U7: =Calculations!B20
I8: TOTAL INGRESOS | K8: =K7 | L8: =L7 | Q8: Honorarios & Profesionales | R8: =-Calculations!B11 | S8: Introducción Marca | T8: 1% del beneficio | U8: =Calculations!B21
I9: 2. COSTES DIRECTOS | Q9: Gastos Comerciales & Admin. | R9: =-Calculations!B17 | S9: BENEFICIO NETO PARA LAWANG (FRAN & PABLO) | T9: Residual | U9: =Calculations!B22
I10: Construcción | J10: 10 villas x 300.000 € | K10: =-Calculations!B3 | L10: =K10/Calculations!B2 | Q10: MARGEN OPERATIVO | R10: =Calculations!B19
I11: Suelo (coste adquisición) | J11: TBD / input editable | K11: =-Calculations!B4 | L11: =K11/Calculations!B2 | Q11: Tonino Lamborghini (3%) | R11: =-Calculations!B20 | S11: RESULTADO FINAL – PHASE I
I12: Urbanización & Infraestructura | J12: Input editable | K12: =-Calculations!B5 | L12: =K12/Calculations!B2 | Q12: Introducción Marca (1%) | R12: =-Calculations!B21 | S12: ="BENEFICIO NETO PARA LAWANG (FRAN & PABLO)"&CHAR(10)&TEXT(Calculations!B22,"€#,##0")&CHAR(10)&TEXT(Calculations!B23,"0.0%")&" SOBRE VENTAS"
I13: Licencias & Permisos | J13: Input editable | K13: =-Calculations!B6 | L13: =K13/Calculations!B2 | Q13: BENEFICIO NETO LAWANG | R13: =Calculations!B22
A14: PROJECT SNAPSHOT – PHASE I | E14: LAND & SITE OVERVIEW | I14: TOTAL COSTES DIRECTOS | K14: =SUM(K10:K13) | L14: =K14/Calculations!B2
A15: Nº Villas | B15: =Assumptions!B2 | E15: Superficie total del proyecto | F15: =TEXT(Assumptions!B6,"#,##0")&" m² (2 ha)" | I15: 3. HONORARIOS & PROFESIONALES
A16: Superficie villa | B16: =TEXT(Assumptions!B4,"#,##0")&" m²" | E16: Precio venta del suelo | F16: =TEXT(Assumptions!B7,"€#,##0")&" /m²" | I16: Nick Maltese Studio | J16: 8% sobre construcción | K16: =-Calculations!B8 | L16: =K17/Calculations!B2
A17: Tipo de villas | B17: 2 & 3 Bedrooms | E17: VALOR POTENCIAL DEL SUELO | F17: =Calculations!B26 | I17: Arquitecto local & ingeniería | J17: Input editable | K17: =-Calculations!B9 | L17: =K18/Calculations!B2 | Q17: MÉTRICAS CLAVE – PHASE I
A18: Precio de venta por villa | B18: =Assumptions!B3 | E18: Uso previsto | F18: Residencial turístico | I18: Otros profesionales técnicos | J18: Input editable | K18: =-Calculations!B10 | L18: =K19/Calculations!B2 | Q18: ="VENTAS (GDV)"&CHAR(10)&TEXT(Calculations!B2,"€#,##0") | S18: ="BENEFICIO NETO LAWANG"&CHAR(10)&TEXT(Calculations!B22,"€#,##0") | V18: ="MARGEN NETO SOBRE VENTAS"&CHAR(10)&TEXT(Calculations!B23,"0.0%")
A19: Ventas totales (GDV) | B19: =Calculations!B2 | E19: Coste adquisición del suelo | F19: =Assumptions!B8 | I19: TOTAL HONORARIOS & PROF. | K19: =SUM(K17:K19) | L19: =K20/Calculations!B2
A20: Inicio comercialización | B20: Mes 2 – 4 | E20: Plusvalía estimada del suelo | F20: =Calculations!B27 | I20: 4. GASTOS COMERCIALES & ADMIN. | Q20: ="ROI SOBRE COSTE TOTAL"&CHAR(10)&TEXT(Calculations!B24,"0.0%") | S20: ="ROI SOBRE INVERSIÓN TOTAL"&CHAR(10)&TEXT(Calculations!B25,"0.0%") | V20: PAYBACK ESTIMADO 12 – 14 MESES
A21: Entrega estimada | B21: Mes 12 – 14 | I21: Marketing & Branding | J21: Input editable | K21: =-Calculations!B12 | L21: =K23/Calculations!B2
I22: Comisiones comerciales (3%) | J22: % de ventas | K22: =-Calculations!B13 | L22: =K24/Calculations!B2
A23: INVERSIÓN & COSTE TOTAL – PHASE I | E23: ESTRUCTURA DE FINANCIACIÓN – PHASE I | I23: Gastos legales & notaría | J23: Input editable | K23: =-Calculations!B14 | L23: =K25/Calculations!B2 | Q23: ¿QUIÉN HACE QUÉ?
A24: Coste adquisición del suelo | B24: =Calculations!B4 | E24: Preventas (30%) | F24: =Calculations!B2*Assumptions!B21 | I24: Gastos administrativos | J24: Input editable | K24: =-Calculations!B15 | L24: =K26/Calculations!B2 | Q24: LAWANG (FRAN & PABLO) Promotor & Desarrollador Propietario del Suelo Construcción & Gestión de Obra Comercialización Beneficio Residual | S24: TONINO LAMBORGHINI Uso de marca 3% del beneficio | U24: INTRODUCCIÓN MARCA Conexión & Introducción 1% del beneficio | W24: NICK MALTESE STUDIO Diseño Arquitectónico Dirección Artística Interiores & Branding 8% sobre coste construcción
A25: Construcción (10 villas) | B25: =Calculations!B3 | E25: Aportación socios (35%) | F25: =Calculations!B2*Assumptions!B22 | I25: Seguros & Contingencias (2%) | J25: % de ventas | K25: =-Calculations!B16 | L25: =K27/Calculations!B2
A26: Urbanización & Infraestructura | B26: =Calculations!B5 | E26: Necesidad financiación / crédito puente (25%) | F26: =Calculations!B2*Assumptions!B23 | I26: TOTAL GASTOS COMERCIALES & ADM. | K26: =SUM(K23:K27) | L26: =K28/Calculations!B2
A27: Licencias & Permisos | B27: =Calculations!B6 | E27: TOTAL FINANCIACIÓN | F27: =SUM(F24:F26) | I27: MARGEN OPERATIVO ANTES DE REPARTOS | K27: =Calculations!B19 | L27: =K29/Calculations!B2
A28: Honorarios & Profesionales | B28: =Calculations!B11
A29: Gastos Comerciales & Admin. | B29: =Calculations!B17
A30: COSTE TOTAL DEL PROYECTO + REPARTOS | B30: =Calculations!B18+Calculations!B20+Calculations!B21
I31: CASH FLOW ESTIMADO – PHASE I (10 VILLAS)
A32: ROADMAP GENERAL DEL PROYECTO (50 VILLAS) | I32: HITO | J32: MES | K32: ENTRADAS (€) | L32: SALIDAS (€) | M32: CASH FLOW ACUMULADO (€)
A33: FASE I 10 VILLAS Meses 0–14 Validación del mercado Generación de caja | C33: → | D33: FASE II 20 VILLAS Meses 14–24 Escalado del proyecto con flujo propio | F33: → | G33: FASE III 20 VILLAS Meses 24–36+ Expansión completa masterplan | I33: Preventas & Reservas (30%) | J33: 2–4 | K33: =Calculations!B2*Assumptions!B21 | L33: 0 | M33: =K33-L33
I34: Inicio Construcción | J34: 6 | K34: 0 | L34: 1500000 | M34: =M33+K34-L34
I35: Avance Obra 30% | J35: 8 | K35: 0 | L35: 1200000 | M35: =M34+K35-L35
I36: Avance Obra 60% | J36: 10 | K36: 0 | L36: 1000000 | M36: =M35+K36-L36
I37: Avance Obra 80% | J37: 12 | K37: 0 | L37: 800000 | M37: =M36+K37-L37
A38: FUENTES / NOTAS DEL MODELO | I38: Entrega & Escrituración (70%) | J38: 12–14 | K38: =Calculations!B2*(1-Assumptions!B21) | L38: =Calculations!B18-SUM(L34:L37) | M38: =M37+K38-L38
A39: Inputs principales: datos proporcionados por Fran/Pablo. Contrato Nick Maltese Studio: branded project, design & artistic direction, 8% del Total Cost of Works; presentación SUMBA X LAMBORGHINI: Wild Coast Sumba Retreat, villas Type A/B, lenguaje arquitectónico y material board. | I39: TOTAL | K39: =SUM(K33:K38) | L39: =SUM(L33:L38) | M39: =M38
I41: RESULTADO FINAL
I42: ESTA PRIMERA FASE FINANCIA EL CRECIMIENTO HACIA EL MASTERPLAN COMPLETO DE 50 VILLAS · 50 M€ VENTAS POTENCIALES · MARCA LAMBORGHINI · DISEÑO & EXPERIENCIA ÚNICOS

Sheet Assumptions
A1: INPUT | B1: VALUE | C1: UNIT | D1: SOURCE / NOTE
A2: Number of villas - Phase I | B2: 10 | C2: villas | D2: User-provided
A3: Sale price per villa | B3: 1000000 | C3: EUR | D3: User-provided
A4: Villa area | B4: 500 | C4: m² | D4: User-provided
A5: Construction cost per villa | B5: 300000 | C5: EUR | D5: User-provided
A6: Total project land | B6: 20000 | C6: m² | D6: User-provided: approx. 2 hectares
A7: Land sale price / target value | B7: 200 | C7: EUR/m² | D7: User-provided
A8: Land acquisition cost - Phase I | B8: 2000000 | C8: EUR | D8: Preliminary assumption from panel; editable
A9: Urbanization & infrastructure | B9: 500000 | C9: EUR | D9: Preliminary estimate; editable
A10: Licenses & permits | B10: 100000 | C10: EUR | D10: Preliminary estimate; editable
A11: Nick Maltese Studio % of construction | B11: 0.08 | C11: % | D11: Engagement Agreement: Design Fee = 8% of TCW
A12: Local architect & engineering | B12: 120000 | C12: EUR | D12: Preliminary estimate; editable
A13: Other technical professionals | B13: 80000 | C13: EUR | D13: Preliminary estimate; editable
... A23: Debt / bridge need | B23: 0.25 | C23: % of sales | D23: Panel financing structure

Sheet Calculations
A1: CALCULATION | B1: FORMULA / VALUE
A2: Gross Sales | B2: =Assumptions!B2*Assumptions!B3
A3: Construction | B3: =Assumptions!B2*Assumptions!B5
A4: Land Acquisition | B4: =Assumptions!B8
A5: Urbanization & Infrastructure | B5: =Assumptions!B9
A6: Licenses & Permits | B6: =Assumptions!B10
A7: Total Direct Costs | B7: =SUM(B3:B6)
A8: Nick Maltese Studio | B8: =B3*Assumptions!B11
A9: Local Architect & Engineering | B9: =Assumptions!B12
A10: Other Technical Professionals | B10: =Assumptions!B13
A11: Total Professional Fees | B11: =SUM(B8:B10)
A12: Marketing & Branding | B12: =Assumptions!B14
A13: Sales Commissions | B13: =B2*Assumptions!B15
A14: Legal & Notary | B14: =Assumptions!B16
A15: Administrative Expenses | B15: =Assumptions!B17
A16: Insurance & Contingencies | B16: =B2*Assumptions!B18
A17: Total Commercial & Admin | B17: =SUM(B12:B16)
A18: Total Project Cost | B18: =B7+B11+B17
A19: Operating Profit Before Splits | B19: =B2-B18
A20: Tonino Lamborghini Split | B20: =B19*Assumptions!B19
A21: Brand Introducer Split | B21: =B19*Assumptions!B20
A22: Net Profit LAWANG | B22: =B19-B20-B21
A23: Net Margin | B23: =B22/B2
A24: ROI on Total Cost | B24: =B22/B18
A25: ROI on Investment | B25: =B22/(B2*Assumptions!B22+B2*Assumptions!B23)
A26: Potential Land Value | B26: =Assumptions!B6*Assumptions!B7
A27: Land Upside | B27: =B26-Assumptions!B8
